{
  "id": "",
  "name": "",
  "font_family": "iconfont",
  "css_prefix_text": "icon-",
  "description": "",
  "glyphs": [
    {
      "icon_id": "591726",
      "name": "wxb主页",
      "font_class": "wxbzhuye",
      "unicode": "e61f",
      "unicode_decimal": 58911
    },
    {
      "icon_id": "17605457",
      "name": "地球",
      "font_class": "diqiu",
      "unicode": "e811",
      "unicode_decimal": 59409
    },
    {
      "icon_id": "18267963",
      "name": "医疗服务",
      "font_class": "yiliaofuwu",
      "unicode": "e99a",
      "unicode_decimal": 59802
    },
    {
      "icon_id": "28337442",
      "name": "li_skull",
      "font_class": "li_skull",
      "unicode": "e6eb",
      "unicode_decimal": 59115
    }
  ]
}
